{
  "slug": "kebap-koenig",
  "imageUrls": [
    "https://example.com/images/kebap-koenig.jpg",
    "https://example.com/photos/kebap_food1.jpg"
  ],
  "name": "Kebap König",
  "district": "Nord",
  "location": {
    "coordinates": {
      "lat": 48.789,
      "lng": 9.178
    },
    "address": {
      "postalCode": "70191",
      "locality": "Stuttgart",
      "sublocality": "Nord",
      "streetAddress": "Nordstraße 3"
    }
  },
  "aiScore": 65,
  "price": 5.0,
  "waitingTime": "SLOW",
  "paymentMethods": ["CASH"],
  "sauceAmount": 45,
  "meatRatio": 55,
  "openingHours": {
    "hours": {
      "mon": [{ "start": "10:00", "end": "23:00" }],
      "tue": [{ "start": "10:00", "end": "23:00" }],
      "wed": [{ "start": "10:00", "end": "23:00" }],
      "thu": [{ "start": "10:00", "end": "23:00" }],
      "fri": [{ "start": "10:00", "end": "24:00" }],
      "sat": [{ "start": "11:00", "end": "24:00" }]
    },
    "timezone": "Europe/Berlin"
  },
  "aiSummary": "Kebap König bietet täglich bis 23 Uhr seinen Service an. Mit einem AI-Score von 65 und einem hohen Fleischanteil von 85% richtet sich das Angebot eher an Fleischliebhaber. Die Wartezeit kann länger ausfallen. Nur Barzahlung möglich."
}
