{
  "slug": "orient-express",
  "imageUrls": ["https://example.com/images/orient_express.jpg"],
  "name": "Orient Express",
  "district": "West",
  "location": {
    "coordinates": {
      "lat": 48.779,
      "lng": 9.16
    },
    "address": {
      "postalCode": "70176",
      "locality": "Stuttgart",
      "sublocality": "West",
      "streetAddress": "Weststraße 8"
    }
  },
  "aiScore": 77,
  "price": 5.5,
  "waitingTime": "AVERAGE",
  "payment": ["CASH", "CREDIT_CARD"],
  "openingHours": {
    "hours": {
      "mon": [{ "start": "11:00", "end": "22:00" }],
      "tue": [{ "start": "11:00", "end": "22:00" }],
      "wed": [{ "start": "11:00", "end": "22:00" }],
      "thu": [{ "start": "11:00", "end": "22:00" }],
      "fri": [{ "start": "11:00", "end": "22:00" }],
      "sat": [{ "start": "11:00", "end": "22:00" }],
      "sun": [{ "start": "11:00", "end": "22:00" }]
    },
    "timezone": "Europe/Berlin"
  },
  "aiSummary": "Orient Express bietet einen guten AI-Score von 77 bei einem fairen Preis. Täglich geöffnet mit konstanten Öffnungszeiten. Zahlung mit Bargeld oder Kreditkarte möglich."
}
